{"title": "Q103178875", "id": "nonns_Q103178875", "links": [{"href": "https:/archaeolink-lod.github.io/samian/collections/nonns_Q103178875/items/index.json", "rel": "items", "type": "application/json", "title": "Collection as JSON"}, {"href": "https:/archaeolink-lod.github.io/samian/collections/nonns_Q103178875/items/indexc.html", "rel": "items", "type": "text/html", "title": "Collection as HTML"}, {"href": "https:/archaeolink-lod.github.io/samian/collections/nonns_Q103178875/items/index.ttl", "rel": "collection", "type": "text/ttl", "title": "Collection as TTL"}], "itemType": "feature", "extent": {"spatial": {"bbox": [[-0.75, 53.633335, -0.75, 53.633335]], "crs": "http://www.opengis.net/def/crs/EPSG/0/4326"}}, "crs": "http://www.opengis.net/def/crs/EPSG/0/4326"}